ubcs_auxiliary/__init__.py
ubcs_auxiliary/_version.py
ubcs_auxiliary/advsleep.py
ubcs_auxiliary/channel_archiver.py
ubcs_auxiliary/hdf5.py
ubcs_auxiliary/multiprocessing.py
ubcs_auxiliary/multithreading.py
ubcs_auxiliary/numerical.py
ubcs_auxiliary/os.py
ubcs_auxiliary/other.py
ubcs_auxiliary/parallel_processing.py
ubcs_auxiliary/plotting.py
ubcs_auxiliary/save_load_object.py
ubcs_auxiliary/saved_property.py
ubcs_auxiliary/threading.py
ubcs_auxiliary/traveling_salesman.py
ubcs_auxiliary/video.py
ubcs_auxiliary/XLI/__init__.py
ubcs_auxiliary/XLI/client.py
ubcs_auxiliary/XLI/hierarchy_instrumentation.py
ubcs_auxiliary/XLI/server.py
ubcs_auxiliary/benchmarks/__init__.py
ubcs_auxiliary/benchmarks/numerical.py
ubcs_auxiliary/tests/__init__.py
ubcs_auxiliary/tests/conftest.py
ubcs_auxiliary/tests/test_adv_sleep.py
ubcs_auxiliary/tests/test_examples.py
ubcs_auxiliary/tests/test_numerical_image.py
ubcs_auxiliary/tests/test_save_load_object.py
ubcs_auxiliary/tests/test_saved_property.py
ubcs_auxiliary/tests/test_threading.py
ubcs_auxiliary/tests/test_traveling_salesman.py
ubcs_auxiliary-0.2.2.dist-info/AUTHORS.rst
ubcs_auxiliary-0.2.2.dist-info/LICENSE
ubcs_auxiliary-0.2.2.dist-info/METADATA
ubcs_auxiliary-0.2.2.dist-info/WHEEL
ubcs_auxiliary-0.2.2.dist-info/entry_points.txt
ubcs_auxiliary-0.2.2.dist-info/top_level.txt
ubcs_auxiliary-0.2.2.dist-info/RECORD
