Metadata-Version: 2.1
Name: ubcs-auxiliary
Version: 0.2.2
Summary: LCP-NIH auxiliary package library
Home-page: https://github.com/vstadnytskyi/auxiliary
Author: Valentyn Stadnytskyi
Author-email: v.stadnytskyi@gmail.com
License: BSD (3-clause)
Platform: UNKNOWN
Classifier: Development Status :: 2 - Pre-Alpha
Classifier: Natural Language :: English
Classifier: Programming Language :: Python :: 3
Requires-Python: >=3.6
Requires-Dist: pyyaml
Requires-Dist: h5py
Requires-Dist: matplotlib
Requires-Dist: numpy
